Metadata-Version: 2.1
Name: niubi
Version: 1.0
Summary: 测试⾃定义模块的发布与安装
Author: drimwai__hlw
Author-email: drimwai@163.com
